yspeed.py
yspeed-0.1.5.dist-info/LICENSE
yspeed-0.1.5.dist-info/METADATA
yspeed-0.1.5.dist-info/WHEEL
yspeed-0.1.5.dist-info/top_level.txt
yspeed-0.1.5.dist-info/RECORD
