Metadata-Version: 2.1
Name: yspeed
Version: 0.1.5
Summary: Yspeed is a library that scrapes the Speedtest site
Home-page: https://github.com/Foufou-exe/Yspeed
Author: Foufou-exe
Author-email: lumina.networks34@gmail.com
Classifier: Development Status :: 3 - Alpha
Classifier: Intended Audience :: Developers
Classifier: License :: OSI Approved :: MIT License
Classifier: Programming Language :: Python :: 3.7
Classifier: Programming Language :: Python :: 3.8
Classifier: Programming Language :: Python :: 3.9
Classifier: Programming Language :: Python :: 3.10
Classifier: Programming Language :: Python :: 3.11
License-File: LICENSE
Requires-Dist: requests
Requires-Dist: selenium
Requires-Dist: rich
Requires-Dist: halo
